combocrypt.py
combocrypt-2.0.0.dist-info/DESCRIPTION.rst
combocrypt-2.0.0.dist-info/METADATA
combocrypt-2.0.0.dist-info/RECORD
combocrypt-2.0.0.dist-info/WHEEL
combocrypt-2.0.0.dist-info/metadata.json
combocrypt-2.0.0.dist-info/top_level.txt
