Metadata-Version: 2.0
Name: combocrypt
Version: 2.0.0
Summary: Variable-length public-key encryption scheme that utilizes a combination of RSA and AES ciphers
Home-page: https://github.com/samrankin1/combocrypt
Author: Sam Rankin
Author-email: sam.rankin@me.com
License: MIT
Keywords: encryption public-key rsa aes
Platform: UNKNOWN
Classifier: Development Status :: 4 - Beta
Classifier: Intended Audience :: Developers
Classifier: License :: OSI Approved :: MIT License
Classifier: Natural Language :: English
Classifier: Operating System :: OS Independent
Classifier: Topic :: Software Development :: Libraries
Classifier: Topic :: Software Development :: Libraries :: Python Modules
Classifier: Topic :: Utilities
Classifier: Programming Language :: Python :: 3
Classifier: Programming Language :: Python :: 3.3
Classifier: Programming Language :: Python :: 3.4
Classifier: Programming Language :: Python :: 3.5
Requires-Dist: cryptography
